pullframe/__init__.py
pullframe/api.py
pullframe/api.pyi
pullframe/coordinator/__init__.py
pullframe/coordinator/zookeeper.py
pullframe/coordinator/zookeeper.pyi
pullframe/exceptions.py
pullframe/exceptions.pyi
pullframe/persist/__init__.py
pullframe/persist/pytables.py
pullframe/persist/pytables.pyi
pullframe/pullframe.py
pullframe/pullframe.pyi
pullframe/py.typed
pullframe/sender.py
pullframe/sender.pyi
pullframe/types.py
pullframe/types.pyi
pullframe-0.1.0.dist-info/LICENSE
pullframe-0.1.0.dist-info/WHEEL
pullframe-0.1.0.dist-info/METADATA
pullframe-0.1.0.dist-info/RECORD
