Metadata-Version: 2.1
Name: pullframe
Version: 0.1.0
Summary: pull based pandas dataframe syncing
Home-page: https://github.com/ghsang/pullframe
License: MIT
Keywords: dataframe,distributed
Author: Hyuksang Gwon
Author-email: gwonhyuksang@gmail.com
Requires-Python: >=3.7,<4.0
Classifier: License :: OSI Approved :: MIT License
Classifier: Programming Language :: Python :: 3
Classifier: Programming Language :: Python :: 3.7
Classifier: Programming Language :: Python :: 3.8
Requires-Dist: aiofiles (>=0.5.0,<0.6.0)
Requires-Dist: fastapi (>=0.58.0,<0.59.0)
Requires-Dist: kazoo (>=2.7.0,<3.0.0)
Requires-Dist: pandas (>=1.0.0,<2.0.0)
Requires-Dist: tables (>=3.6.1,<4.0.0)
Project-URL: Repository, https://github.com/ghsang/pullframe
